{
  "tourTitle": "探索桃子腳的建築密碼",
  "tourSubtitle": "時空膠囊導覽 — 連結土地與記憶的校園巡禮",
  "categories": [
    { "id": "history", "name": "校史記憶", "icon": "🏛️", "color": "#b71c1c" },
    { "id": "art", "name": "藝術風景", "icon": "🎨", "color": "#7c3aed" },
    { "id": "nature", "name": "生態土地", "icon": "🌿", "color": "#059669" },
    { "id": "campus", "name": "校園生活", "icon": "🏫", "color": "#2563eb" }
  ],
  "stops": [
    {
      "id": "stop-gate",
      "title": "校名銜",
      "subtitle": "桃子腳的第一道密碼",
      "category": "history",
      "markerId": "pointC",
      "mapX": 2610,
      "mapY": 4000,
      "zoom": 2.0,
      "icon": "🚪",
      "color": "#b71c1c",
      "coverImage": "uploads/IMG_20231128_011046_00_merged.jpg",
      "images": ["uploads/IMG_20231128_011046_00_merged.jpg"],
      "brief": "走進校門，首先映入眼簾的是承載百年記憶的「校名銜」，它是桃子腳與土地連結的起點。",
      "story": "桃子腳國中小的校門口，矗立著一座獨特的「校名銜」。這不只是學校的標誌，更是與這片土地的情感連結。校名銜的設計靈感源自於早期的牛車意象，象徵著先民在這片土地上辛勤耕作的精神。每當清晨的第一道陽光灑落在校名銜上，金色的光輝彷彿在訴說著這片土地的故事。從日治時期的公學校到今天的實驗教育典範，桃子腳走過了近百年的歲月，而校名銜始終默默地守候在這裡，迎接每一位回家的孩子。",
      "funFact": "你知道嗎？「桃子腳」這個地名源自於早期這裡種滿了桃樹，而學校正好位於桃園的尾端（腳），因此得名。",
      "relatedImages": ["IMG_20231128_011046_00_merged.jpg", "IMG_20231205_004043_00_merged.jpg"]
    },
    {
      "id": "stop-c-building",
      "title": "C 棟大樓 — 學勤廊",
      "subtitle": "朗朗書聲中的求學路",
      "category": "campus",
      "markerId": "pointC",
      "mapX": 2610,
      "mapY": 4000,
      "zoom": 1.5,
      "icon": "📚",
      "color": "#2563eb",
      "coverImage": "uploads/IMG_20231205_004043_00_merged.jpg",
      "images": ["uploads/IMG_20231205_004043_00_merged.jpg", "uploads/IMG_20231205_004232_00_merged.jpg"],
      "brief": "學勤廊連接了校長室與教導處，是校園行政與教學的核心地帶。",
      "story": "C 棟大樓內的「學勤廊」，名字取自「勤勉向學」之意。走在這條走廊上，你可以看到兩側牆面上展示著學生們的學習成果與創作。這裡不只是通行的空間，更是一座無牆的展覽館。走廊的盡頭是校長室，而另一端連接教導處，象徵著教育的傳承與延續。每天早晨，學生們踏著輕快的腳步穿過學勤廊，開始一天的學習旅程。這裡的每一個角落都充滿了成長的足跡。",
      "funFact": "學勤廊的360全景照片讓你可以環顧四周，感受真實的校園氛圍！",
      "relatedImages": ["IMG_20231205_004043_00_merged.jpg", "IMG_20231205_004232_00_merged.jpg"]
    },
    {
      "id": "stop-original-court",
      "title": "原庭",
      "subtitle": "與土地對話的圓形廣場",
      "category": "nature",
      "markerId": "pointK",
      "mapX": 1390,
      "mapY": 1820,
      "zoom": 1.8,
      "icon": "🌳",
      "color": "#059669",
      "coverImage": "uploads/IMG_20231205_005826_00_merged.jpg",
      "images": ["uploads/IMG_20231205_005826_00_merged.jpg", "uploads/IMG_20231205_010006_00_merged.jpg"],
      "brief": "原庭是校園中最具代表性的生態空間，融合了自然與人文之美。",
      "story": "「原庭」的名字蘊含著「回歸原始、尊重自然」的教育理念。這個圓形的戶外空間是桃子腳實驗教育的重要場域。學生們在這裡觀察季節的變化、種植植物、觀察昆蟲，用五感去體驗土地的脈動。原庭的設計打破了傳統校園的方正格局，以流動的曲線和自然素材營造出一個親近大地的學習環境。在這裡，教學不再局限於教室之內，而是延伸到這片充滿生命力的土地上。",
      "funFact": "原庭的圓形設計象徵著「圓滿」與「包容」，也呼應了原住民族群對大地母親的崇敬。",
      "relatedImages": ["IMG_20231205_005826_00_merged.jpg", "IMG_20231205_010006_00_merged.jpg"]
    },
    {
      "id": "stop-diamond-stage",
      "title": "鑽石舞台",
      "subtitle": "閃耀的表演天地",
      "category": "art",
      "markerId": "pointH",
      "mapX": 2660,
      "mapY": 2980,
      "zoom": 1.8,
      "icon": "💎",
      "color": "#7c3aed",
      "coverImage": "uploads/IMG_20231205_004909_00_merged.jpg",
      "images": ["uploads/IMG_20231205_004909_00_merged.jpg"],
      "brief": "鑽石舞台是學生展現才華的表演空間，承載著無數精彩的校園記憶。",
      "story": "「鑽石舞台」得名於其獨特的菱形（鑽石形）設計。這個戶外表演空間是桃子腳藝術教育的重要場域。每年的畢業典禮、校慶表演、社區藝文活動都在這裡舉行。舞台的設計考量了聲學效果與觀眾視角，讓每一位觀眾都能享受最佳的表演體驗。在鑽石舞台上，無數學生從怯生生的初登場，蜕變為自信閃耀的表演者。這個舞台不只是一座建築，更是培育夢想的搖籃。",
      "funFact": "鑽石舞台的菱形設計靈感來自於台灣原住民的傳統幾何圖案，象徵著堅毅與閃耀。",
      "relatedImages": ["IMG_20231205_004909_00_merged.jpg"]
    },
    {
      "id": "stop-k-building",
      "title": "K 棟大樓 — 藝術教室",
      "subtitle": "色彩與音符的殿堂",
      "category": "art",
      "markerId": "pointK",
      "mapX": 1390,
      "mapY": 1820,
      "zoom": 1.5,
      "icon": "🎨",
      "color": "#7c3aed",
      "coverImage": "uploads/IMG_20231205_005826_00_merged.jpg",
      "images": [],
      "brief": "K 棟匯聚了視覺藝術教室、音樂教室與演藝廳，是校園的藝術心臟。",
      "story": "K 棟大樓又被稱為「原庭」旁的藝術殿堂。這裡有設備完善的視覺藝術教室、音樂教室，以及可以容納全校師生的演藝廳。在視覺藝術教室裡，學生們用水彩、蠟筆、黏土等媒材創作，將心中的世界化為具象的作品。音樂教室則傳出悠揚的琴聲與歌聲，培養學生的音樂素養。每年的藝術季，K 棟都會變身為一座巨大的展覽空間，展示學生們一整年的學習成果。",
      "funFact": "K 棟的「原庭」之名，源自於旁邊的原庭生態園區，象徵藝術與自然的融合。",
      "relatedImages": []
    },
    {
      "id": "stop-e-building",
      "title": "E 棟大樓 — 國中部",
      "subtitle": "青春的起點",
      "category": "campus",
      "markerId": "pointE",
      "mapX": 2700,
      "mapY": 1700,
      "zoom": 1.5,
      "icon": "🎵",
      "color": "#2563eb",
      "coverImage": "",
      "images": [],
      "brief": "E 棟是國中部的教學基地，涵蓋音樂、視覺藝術與理化實驗空間。",
      "story": "E 棟大樓是國中部學生的主要學習空間。這裡不只有一般教室，還設有專業的音樂教室、視覺藝術教室以及理化教室。在這裡，國中部的同學們開始接觸更深入的學科知識，同時也有機會在專業教室中探索自己的興趣。E 棟的走廊上經常可以看到學生們的創作展示，從科學實驗報告到藝術作品，呈現出桃子腳跨領域教學的成果。",
      "funFact": "E 棟的理化教室配備了完整的實驗設備，讓學生能親手操作實驗，體驗科學的奧妙。",
      "relatedImages": []
    },
    {
      "id": "stop-b-building",
      "title": "B 棟大樓 — 健康中心",
      "subtitle": "守護健康的溫暖角落",
      "category": "campus",
      "markerId": "pointB",
      "mapX": 1330,
      "mapY": 4050,
      "zoom": 1.5,
      "icon": "🏥",
      "color": "#2563eb",
      "coverImage": "",
      "images": [],
      "brief": "B 棟集合了室內運動空間、健康中心、教務處與電腦教室。",
      "story": "B 棟大樓是校園中功能最多元的建築之一。一樓的室內運動空間為師生提供了不受天候影響的運動場所，無論是颱風天還是下雨天，學生們都能在這裡繼續活動身體。健康中心是守護全校師生健康的温暖角落，護理師總是用專業且耐心的態度照顧每一位需要幫助的同學。此外，教務處和電腦教室也設在B棟，讓這裡成為校園行政與數位學習的重要樞紐。",
      "funFact": "B 棟的室內運動空間曾多次舉辦社區羽球比賽，是學校與社區交流的重要場域。",
      "relatedImages": []
    },
    {
      "id": "stop-g-building",
      "title": "G 棟大樓 — 小教處",
      "subtitle": "啟蒙教育的溫暖基地",
      "category": "history",
      "markerId": "pointG",
      "mapX": 1500,
      "mapY": 3030,
      "zoom": 1.5,
      "icon": "📖",
      "color": "#b71c1c",
      "coverImage": "",
      "images": [],
      "brief": "G 棟匯集了小教處、國小部圖書館與多功能英桃教室。",
      "story": "G 棟大樓是國小部的核心所在。小教處在這裡統籌國小部的各項教學事務，而國小部圖書館則是孩子們探索知識的寶庫。圖書館內收藏了豐富的繪本、科普讀物和兒童文學，每一本書都是一扇通往新世界的窗戶。特別值得一提的是「英桃教室」——這個多功能教室的名字取自「英語」與「桃子腳」的結合，是學校推動雙語教育的重要場域。",
      "funFact": "「英桃教室」的名字結合了英語(English)和桃子腳(Tao-Zi-Jiao)的縮寫，是學校雙語教學的創意展現。",
      "relatedImages": ["IMG_20231205_010953_00_merged.jpg"]
    },
    {
      "id": "stop-playground",
      "title": "操場與風雨操場",
      "subtitle": "奔馳的青春與汗水",
      "category": "nature",
      "markerId": "marker-1780482876930",
      "mapX": 2944,
      "mapY": 944,
      "zoom": 0.8,
      "icon": "🏃",
      "color": "#059669",
      "coverImage": "",
      "images": [],
      "brief": "寬廣的操場與風雨操場，讓學生不論晴雨都能盡情運動。",
      "story": "桃子腳的操場是校園中最開闊的空間。紅色的PU跑道環繞著綠茵足球場，每到下課時間，這裡就充滿了歡笑聲與奔跑的身影。旁邊的風雨操場更是貼心的設計，即使在台灣多雨的季節，學生們也能在遮蔽的空間中繼續運動。操場的邊緣種植了多種樹木，形成了一道天然的綠色屏障，不僅美化了校園環境，也為師生提供了遮蔭休憩的場所。這裡是體育課、晨間活動和校慶運動會的主要場地。",
      "funFact": "操場周圍的樹木中，有幾棵是建校時就種下的老樹，見證了桃子腳數十年的成長。",
      "relatedImages": []
    },
    {
      "id": "stop-i-building",
      "title": "I 棟 & J 棟 — 國小部教室",
      "subtitle": "童年的歡樂城堡",
      "category": "campus",
      "markerId": "pointI",
      "mapX": 830,
      "mapY": 2500,
      "zoom": 1.2,
      "icon": "🏰",
      "color": "#2563eb",
      "coverImage": "",
      "images": [],
      "brief": "I 棟與 J 棟是國小部的主要教室，承載著孩子們最純真的童年回憶。",
      "story": "走在 I 棟與 J 棟之間的連廊上，你會感受到一股純真而活潑的氣息。這裡是國小部一至六年級的教室所在，每一天都上演著無數溫馨的故事。教室的窗台上擺放著學生們親手栽培的盆栽，走廊的牆面則展示著他們的美術作品和學習歷程。I 棟與 J 棟的建築風格保留了早期校舍的樸實之美，同時也融入了現代化的教學設施，讓傳統與創新在這裡和諧共存。",
      "funFact": "每到春天，J 棟旁的花圃會開滿波斯菊，成為校園中最受歡迎的拍照景點。",
      "relatedImages": []
    },
    {
      "id": "stop-l-building",
      "title": "L 棟大樓 — 幼兒園",
      "subtitle": "萌芽的起始",
      "category": "history",
      "markerId": "pointL",
      "mapX": 770,
      "mapY": 930,
      "zoom": 1.5,
      "icon": "🌱",
      "color": "#b71c1c",
      "coverImage": "",
      "images": [],
      "brief": "L 棟是幼兒園的所在地，也是桃子腳教育旅程的第一站。",
      "story": "L 棟大樓是桃子腳教育旅程的起點——幼兒園。在這裡，最小的桃子腳學子們展開了他們的校園生活。幼兒園的教室色彩鮮明、充滿童趣，每一個角落都經過精心設計，為孩子們創造一個安全、溫馨且充滿探索樂趣的學習環境。從戶外的溜滑梯到室內的閱讀角，從種植園區到藝術創作區，L 棟為幼兒提供了多元的體驗機會，讓他們在遊戲中學習，在探索中成長。",
      "funFact": "幼兒園的戶外花園裡有一棵「許願樹」，孩子們會把心願寫在彩色紙條上掛在樹枝上。",
      "relatedImages": []
    }
  ]
}